strawberry_django_plus/__init__.py
strawberry_django_plus/descriptors.py
strawberry_django_plus/directives.py
strawberry_django_plus/field.py
strawberry_django_plus/filters.py
strawberry_django_plus/gql/__init__.py
strawberry_django_plus/gql/django.py
strawberry_django_plus/integrations/__init__.py
strawberry_django_plus/integrations/guardian.py
strawberry_django_plus/management/commands/__init__.py
strawberry_django_plus/management/commands/export_schema.py
strawberry_django_plus/middlewares/__init__.py
strawberry_django_plus/middlewares/user_warmup.py
strawberry_django_plus/mutations/__init__.py
strawberry_django_plus/mutations/fields.py
strawberry_django_plus/mutations/resolvers.py
strawberry_django_plus/optimizer.py
strawberry_django_plus/ordering.py
strawberry_django_plus/permissions.py
strawberry_django_plus/py.typed
strawberry_django_plus/relay.py
strawberry_django_plus/settings.py
strawberry_django_plus/test/__init__.py
strawberry_django_plus/test/client.py
strawberry_django_plus/type.py
strawberry_django_plus/types.py
strawberry_django_plus/utils/__init__.py
strawberry_django_plus/utils/aio.py
strawberry_django_plus/utils/inspect.py
strawberry_django_plus/utils/pyutils.py
strawberry_django_plus/utils/query.py
strawberry_django_plus/utils/resolvers.py
strawberry_django_plus/utils/typing.py
strawberry_django_plus-3.1.1.dist-info/LICENSE
strawberry_django_plus-3.1.1.dist-info/METADATA
strawberry_django_plus-3.1.1.dist-info/WHEEL
strawberry_django_plus-3.1.1.dist-info/RECORD
