Metadata-Version: 2.1
Name: strawberry-django-plus
Version: 3.1.1
Summary: Enhanced Strawberry GraphQL integration with Django
Home-page: https://github.com/blb-ventures/strawberry-django-plus
License: MIT
Keywords: strawberry,django,graphql,relay,optimizer
Author: Thiago Bellini Ribeiro
Author-email: thiago@bellini.dev
Requires-Python: >=3.8,<4.0
Classifier: Development Status :: 5 - Production/Stable
Classifier: Environment :: Web Environment
Classifier: Framework :: Django
Classifier: Framework :: Django :: 3.2
Classifier: Framework :: Django :: 4.0
Classifier: Framework :: Django :: 4.1
Classifier: Framework :: Django :: 4.2
Classifier: Intended Audience :: Developers
Classifier: License :: OSI Approved :: MIT License
Classifier: Operating System :: OS Independent
Classifier: Programming Language :: Python
Classifier: Programming Language :: Python :: 3
Classifier: Programming Language :: Python :: 3.8
Classifier: Programming Language :: Python :: 3.9
Classifier: Programming Language :: Python :: 3.10
Classifier: Programming Language :: Python :: 3.11
Provides-Extra: enum
Requires-Dist: django (>=3.2)
Requires-Dist: django-choices-field (>=2.0) ; extra == "enum"
Requires-Dist: strawberry-graphql (>=0.187.5)
Requires-Dist: strawberry-graphql-django (>=0.9.4,<0.10.0)
Requires-Dist: typing-extensions (>=4.2.0)
Project-URL: Documentation, https://strawberry-django-plus.readthedocs.io
Project-URL: Repository, https://github.com/blb-ventures/strawberry-django-plus
